unleashed_chat/__init__.py
unleashed_chat/cli.py
unleashed_chat/config.py
unleashed_chat/config_handler.py
unleashed_chat/main.py
unleashed_chat/main_old.py
unleashed_chat/openai_client.py
unleashed_chat/session.py
unleashed_chat_cli/__init__.py
unleashed_chat_cli/main.py
unleashed_chat-0.1.4.dist-info/METADATA
unleashed_chat-0.1.4.dist-info/WHEEL
unleashed_chat-0.1.4.dist-info/entry_points.txt
unleashed_chat-0.1.4.dist-info/top_level.txt
unleashed_chat-0.1.4.dist-info/RECORD
