Metadata-Version: 2.1
Name: unleashed-chat
Version: 0.1.4
Summary: A CLI wrapper for Unleashed.chat's chatbot service.
Home-page: https://github.com/reecehunter/unleashed-chat
Author: Reece Hunter
Classifier: Programming Language :: Python :: 3
Classifier: License :: OSI Approved :: MIT License
Classifier: Operating System :: OS Independent
Requires-Python: >=3.7.1
Requires-Dist: openai
